nlpir/__init__.py
nlpir/cluster.py
nlpir/deep_classifier.py
nlpir/doc_extractor.py
nlpir/exception.py
nlpir/eye_checker.py
nlpir/ictclas.py
nlpir/key_extract.py
nlpir/key_scanner.py
nlpir/new_word_finder.py
nlpir/sentiment_analysis.py
nlpir/summary.py
nlpir/text_similarity.py
nlpir/tools.py
nlpir/Data/BIG2GBK.map
nlpir/Data/BIG5.pdat
nlpir/Data/BIG5.wordlist
nlpir/Data/BiWord.big
nlpir/Data/CETrans.dict
nlpir/Data/ChnDict.dct
nlpir/Data/ChnSenti-76005.txt
nlpir/Data/ChnStopList.txt
nlpir/Data/CodeTrans.model
nlpir/Data/Configure.xml
nlpir/Data/CoreDict.pdat
nlpir/Data/CoreDict.pos
nlpir/Data/CoreDict.unig
nlpir/Data/CoreDict.wordlist
nlpir/Data/Dict.pdat
nlpir/Data/Dict.wordlist
nlpir/Data/EngDict.dct
nlpir/Data/EngStopList.txt
nlpir/Data/FTU8.pdat
nlpir/Data/FTU8.wordlist
nlpir/Data/FTU82GBK.map
nlpir/Data/FieldDict.pdat
nlpir/Data/FieldDict.pos
nlpir/Data/FieldDict.wordlist
nlpir/Data/GBK.pdat
nlpir/Data/GBK.wordlist
nlpir/Data/GBK2BIG.map
nlpir/Data/GBK2FTU8.map
nlpir/Data/GBK2GBKA.map
nlpir/Data/GBK2GBKC.map
nlpir/Data/GBK2UTF.map
nlpir/Data/GBK2UTF8.map
nlpir/Data/GBKA.pdat
nlpir/Data/GBKA.wordlist
nlpir/Data/GBKA2GBK.map
nlpir/Data/GBKA2UTF.map
nlpir/Data/GBKC.pdat
nlpir/Data/GBKC.wordlist
nlpir/Data/GBKC2GBK.map
nlpir/Data/GranDict.pdat
nlpir/Data/GranDict.pos
nlpir/Data/ICTCLAS30.ctx
nlpir/Data/ICTCLAS_First.map
nlpir/Data/ICTPOS.map
nlpir/Data/KGB-Configure.json
nlpir/Data/KGB-Configure.xml
nlpir/Data/KGB_Manager.dat
nlpir/Data/KeyBlackList.pdat
nlpir/Data/NLPIR.ctx
nlpir/Data/NLPIR_First.map
nlpir/Data/NewWord.lst
nlpir/Data/PKU.map
nlpir/Data/PKU_First.map
nlpir/Data/SpellError.map
nlpir/Data/SpellError.map.export
nlpir/Data/SpellError.pdat
nlpir/Data/SpellError.wordlist
nlpir/Data/SpellError.wordlist.export
nlpir/Data/SpellError_userdict.txt
nlpir/Data/UTF2GBK.map
nlpir/Data/UTF2GBKA.map
nlpir/Data/UTF8.pdat
nlpir/Data/UTF8.txt
nlpir/Data/UTF8.wordlist
nlpir/Data/UTF82GBK.map
nlpir/Data/UserDict.pdat
nlpir/Data/Xing.pdat
nlpir/Data/Xing.wordlist
nlpir_python-0.9.15.1.dist-info/LICENSE
nlpir_python-0.9.15.1.dist-info/METADATA
nlpir_python-0.9.15.1.dist-info/WHEEL
nlpir_python-0.9.15.1.dist-info/entry_points.txt
nlpir_python-0.9.15.1.dist-info/top_level.txt
nlpir_python-0.9.15.1.dist-info/RECORD
