Metadata-Version: 2.1
Name: nlpir-python
Version: 0.9.15.1
Summary: NLPIR-python A python wrapper and toolkit for NLPIR
Home-page: UNKNOWN
Author: yangyaofei, LingJoin Co.,Ltd.
Author-email: yangyaofei@gmail.com
License: MIT
Keywords: nlpir,nlp,Chinese word segmentation,ictclas,CWS
Platform: win32
Platform: win64
Platform: linux32
Platform: linux64darwin
Classifier: License :: OSI Approved :: MIT License
Classifier: Natural Language :: Chinese (Simplified)
Classifier: Operating System :: MacOS :: MacOS X
Classifier: Operating System :: Microsoft :: Windows
Classifier: Operating System :: POSIX :: Linux
Classifier: Topic :: Text Processing :: Linguistic
Classifier: Topic :: Software Development :: Libraries :: Python Modules
Requires-Python: >=3.6
Requires-Dist: requests
Requires-Dist: pydantic (>=1.8.2)
Requires-Dist: typing
